emojizones/__init__.py
emojizones/convert.py
emojizones/lookup.py
emojizones-0.3.2.dist-info/LICENSE
emojizones-0.3.2.dist-info/METADATA
emojizones-0.3.2.dist-info/WHEEL
emojizones-0.3.2.dist-info/top_level.txt
emojizones-0.3.2.dist-info/RECORD
