Metadata-Version: 2.1
Name: emojizones
Version: 0.3.2
Summary: A helper library to convert dates between timezone using emojiis
Home-page: https://github.com/EmilStenstrom/emojizones/
Author: Emil Stenström
Author-email: em@kth.se
License: UNKNOWN
Keywords: emojizones,conll,conll-u,parser,nlp
Platform: UNKNOWN
Classifier: Programming Language :: Python
Classifier: Programming Language :: Python :: 3.6
Classifier: Programming Language :: Python :: 3.7
Classifier: Programming Language :: Python :: 3.8
Classifier: Programming Language :: Python :: 3.9
Classifier: Operating System :: OS Independent
Requires-Dist: pytz
Requires-Dist: grapheme
